orbittools/__init__.py
orbittools/kepler.py
orbittools/tle.py
orbittools/transforms.py
orbittools-0.1.0.dist-info/METADATA
orbittools-0.1.0.dist-info/WHEEL
orbittools-0.1.0.dist-info/licenses/LICENSE
orbittools-0.1.0.dist-info/RECORD
